xlsp/__init__.py
xlsp/xlsp.py
xlsp-0.1.1.dist-info/METADATA
xlsp-0.1.1.dist-info/WHEEL
xlsp-0.1.1.dist-info/top_level.txt
xlsp-0.1.1.dist-info/RECORD
